pocket_to_sqlite/__init__.py
pocket_to_sqlite/cli.py
pocket_to_sqlite/utils.py
pocket_to_sqlite-0.2.3.dist-info/LICENSE
pocket_to_sqlite-0.2.3.dist-info/METADATA
pocket_to_sqlite-0.2.3.dist-info/WHEEL
pocket_to_sqlite-0.2.3.dist-info/entry_points.txt
pocket_to_sqlite-0.2.3.dist-info/top_level.txt
pocket_to_sqlite-0.2.3.dist-info/RECORD
