Metadata-Version: 2.1
Name: pocket-to-sqlite
Version: 0.2.3
Summary: Create a SQLite database containing data from your Pocket account
Author: Simon Willison
License: Apache-2.0
Project-URL: homepage, https://github.com/dogsheep/pocket-to-sqlite
Project-URL: Changelog, https://github.com/dogsheep/pocket-to-sqlite/releases
Project-URL: Issues, https://github.com/dogsheep/pocket-to-sqlite/issues
Project-URL: CI, https://github.com/dogsheep/pocket-to-sqlite/actions
Classifier: License :: OSI Approved :: Apache Software License
Requires-Python: >3.7
License-File: LICENSE
Requires-Dist: sqlite-utils (>=2.4.4)
Requires-Dist: click
Requires-Dist: requests
Provides-Extra: test
Requires-Dist: pytest ; extra == 'test'
